{
  "project_info": {
    "project_number": "1028954119670",
    "firebase_url": "https://hibiki-bec51.firebaseio.com",
    "project_id": "hibiki-bec51",
    "storage_bucket": "hibiki-bec51.appspot.com"
  },
  "client": [
    {
      "client_info": {
        "mobilesdk_app_id": "1:1028954119670:android:697f43ed6e2c2ea2d93bd7",
        "android_client_info": {
          "package_name": "in.surajsau.trace.nintendo"
        }
      },
      "oauth_client": [
        {
          "client_id": "1028954119670-ch92m7nk6b3oi4p4nfv4svis655hfed0.apps.googleusercontent.com",
          "client_type": 1,
          "android_info": {
            "package_name": "in.surajsau.trace.nintendo",
            "certificate_hash": "44ee6420e0c9fb4c5a5b6994d732d9b0f031bda4"
          }
        },
        {
          "client_id": "1028954119670-g49eb54lah20c9vj0l2acesh42fjdm0i.apps.googleusercontent.com",
          "client_type": 3
        }
      ],
      "api_key": [
        {
          "current_key": "AIzaSyDwVYQG5Nd_STDHKJE8UBQKf0yeERxRVAk"
        }
      ],
      "services": {
        "appinvite_service": {
          "other_platform_oauth_client": [
            {
              "client_id": "1028954119670-g49eb54lah20c9vj0l2acesh42fjdm0i.apps.googleusercontent.com",
              "client_type": 3
            },
            {
              "client_id": "1028954119670-olvur329rhckt6fssico80v0ie8227n6.apps.googleusercontent.com",
              "client_type": 2,
              "ios_info": {
                "bundle_id": "in.surajsau.hibiki"
              }
            }
          ]
        }
      }
    },
    {
      "client_info": {
        "mobilesdk_app_id": "1:1028954119670:android:48383da6c9d76308d93bd7",
        "android_client_info": {
          "package_name": "in.surajsau.trace.github"
        }
      },
      "oauth_client": [
        {
          "client_id": "1028954119670-8dpdkeb72vmganlakqr1i78pgk4il2a0.apps.googleusercontent.com",
          "client_type": 1,
          "android_info": {
            "package_name": "in.surajsau.trace.github",
            "certificate_hash": "44ee6420e0c9fb4c5a5b6994d732d9b0f031bda4"
          }
        },
        {
          "client_id": "1028954119670-g49eb54lah20c9vj0l2acesh42fjdm0i.apps.googleusercontent.com",
          "client_type": 3
        }
      ],
      "api_key": [
        {
          "current_key": "AIzaSyDwVYQG5Nd_STDHKJE8UBQKf0yeERxRVAk"
        }
      ],
      "services": {
        "appinvite_service": {
          "other_platform_oauth_client": [
            {
              "client_id": "1028954119670-g49eb54lah20c9vj0l2acesh42fjdm0i.apps.googleusercontent.com",
              "client_type": 3
            },
            {
              "client_id": "1028954119670-olvur329rhckt6fssico80v0ie8227n6.apps.googleusercontent.com",
              "client_type": 2,
              "ios_info": {
                "bundle_id": "in.surajsau.hibiki"
              }
            }
          ]
        }
      }
    }
  ],
  "configuration_version": "1"
}